pagelets/__init__.py
pagelets/admin.py
pagelets/conf.py
pagelets/forms.py
pagelets/lookups.py
pagelets/models.py
pagelets/sitemaps.py
pagelets/utils.py
pagelets/validators.py
pagelets/views.py
pagelets/migrations/0001_initial.py
pagelets/migrations/__init__.py
pagelets/static/css/pagelets.css
pagelets/static/css/wymeditor.admin.css
pagelets/static/js/pagelets.js
pagelets/static/wymeditor/jquery.wymeditor.js
pagelets/static/wymeditor/jquery.wymeditor.min.js
pagelets/static/wymeditor/jquery.wymeditor.pack.js
pagelets/static/wymeditor/iframe/default/lbl-blockquote.png
pagelets/static/wymeditor/iframe/default/lbl-h1.png
pagelets/static/wymeditor/iframe/default/lbl-h2.png
pagelets/static/wymeditor/iframe/default/lbl-h3.png
pagelets/static/wymeditor/iframe/default/lbl-h4.png
pagelets/static/wymeditor/iframe/default/lbl-h5.png
pagelets/static/wymeditor/iframe/default/lbl-h6.png
pagelets/static/wymeditor/iframe/default/lbl-p.png
pagelets/static/wymeditor/iframe/default/lbl-pre.png
pagelets/static/wymeditor/iframe/default/wymiframe.css
pagelets/static/wymeditor/iframe/default/wymiframe.html
pagelets/static/wymeditor/lang/bg.js
pagelets/static/wymeditor/lang/ca.js
pagelets/static/wymeditor/lang/cs.js
pagelets/static/wymeditor/lang/cy.js
pagelets/static/wymeditor/lang/de.js
pagelets/static/wymeditor/lang/en.js
pagelets/static/wymeditor/lang/es.js
pagelets/static/wymeditor/lang/fa.js
pagelets/static/wymeditor/lang/fi.js
pagelets/static/wymeditor/lang/fr.js
pagelets/static/wymeditor/lang/gl.js
pagelets/static/wymeditor/lang/he.js
pagelets/static/wymeditor/lang/hr.js
pagelets/static/wymeditor/lang/hu.js
pagelets/static/wymeditor/lang/it.js
pagelets/static/wymeditor/lang/nb.js
pagelets/static/wymeditor/lang/nl.js
pagelets/static/wymeditor/lang/nn.js
pagelets/static/wymeditor/lang/pl.js
pagelets/static/wymeditor/lang/pt-br.js
pagelets/static/wymeditor/lang/pt.js
pagelets/static/wymeditor/lang/ru.js
pagelets/static/wymeditor/lang/sv.js
pagelets/static/wymeditor/lang/tr.js
django_pagelets-2.0.0.dist-info/LICENSE.txt
django_pagelets-2.0.0.dist-info/METADATA
django_pagelets-2.0.0.dist-info/WHEEL
django_pagelets-2.0.0.dist-info/top_level.txt
django_pagelets-2.0.0.dist-info/RECORD
