Metadata-Version: 2.1
Name: django-pagelets
Version: 2.0.0
Summary: Simple, flexible app for integrating static, unstructured content in a Django site
Home-page: https://github.com/caktus/django-pagelets/
Author: Caktus Consulting Group
Author-email: solutions@caktusgroup.com
License: BSD
Platform: UNKNOWN
Classifier: Environment :: Web Environment
Classifier: Framework :: Django
Classifier: Topic :: Internet :: WWW/HTTP :: Dynamic Content
Classifier: Intended Audience :: Developers
Classifier: License :: OSI Approved :: BSD License
Classifier: Programming Language :: Python :: 3
Classifier: Programming Language :: Python :: 3
Classifier: Programming Language :: Python :: 3.6
Classifier: Programming Language :: Python :: 3.7
Classifier: Programming Language :: Python :: 3.8
Classifier: Programming Language :: Python :: 3.9
Classifier: Topic :: Software Development :: Libraries :: Python Modules
Classifier: Development Status :: 5 - Production/Stable
Classifier: Operating System :: OS Independent
Requires-Dist: django-selectable (>=1.2.1)
Requires-Dist: django-taggit (>=0.12.1)
